README.md
setup.py
rolimons/__init__.py
rolimons/exceptions.py
rolimons/item.py
rolimons/player.py
rolimons/utils.py
rolimons.egg-info/PKG-INFO
rolimons.egg-info/SOURCES.txt
rolimons.egg-info/dependency_links.txt
rolimons.egg-info/requires.txt
rolimons.egg-info/top_level.txt