Metadata-Version: 2.1
Name: rolimons
Version: 2.7.5
Summary: Rolimons API Wrapper
Home-page: https://github.com/wa1ker38552/rolimons.py
Author: walker
License: UNKNOWN
Platform: UNKNOWN
Requires-Python: >=3.7
